README.md
setup.cfg
setup.py
udemy_gaussian_binomial/Binomialdistribution.py
udemy_gaussian_binomial/Gaussiandistribution.py
udemy_gaussian_binomial/Generaldistribution.py
udemy_gaussian_binomial/__init__.py
udemy_gaussian_binomial.egg-info/PKG-INFO
udemy_gaussian_binomial.egg-info/SOURCES.txt
udemy_gaussian_binomial.egg-info/dependency_links.txt
udemy_gaussian_binomial.egg-info/not-zip-safe
udemy_gaussian_binomial.egg-info/top_level.txt