Metadata-Version: 2.1
Name: udemy-gaussian-binomial
Version: 0.1
Summary: Gaussian distributions
License: UNKNOWN
Platform: UNKNOWN
